first.py
first-2.0.1.dist-info/DESCRIPTION.rst
first-2.0.1.dist-info/METADATA
first-2.0.1.dist-info/pydist.json
first-2.0.1.dist-info/RECORD
first-2.0.1.dist-info/top_level.txt
first-2.0.1.dist-info/WHEEL
